easy_eval
