Metadata-Version: 2.1
Name: easy-lm-eval
Version: 0.1.2
Summary: A library for easy evaluation of language models
Home-page: https://github.com/Anindyadeep/easyeval
Author: Anindyadeep
Author-email: proanindyadeep@gmail.com
License: UNKNOWN
Platform: UNKNOWN
